LICENSE
README.rst
setup.py
keras_model_hub/__init__.py
keras_model_hub.egg-info/PKG-INFO
keras_model_hub.egg-info/SOURCES.txt
keras_model_hub.egg-info/dependency_links.txt
keras_model_hub.egg-info/not-zip-safe
keras_model_hub.egg-info/requires.txt
keras_model_hub.egg-info/top_level.txt