Metadata-Version: 2.1
Name: keras-model-hub
Version: 0.0.1
Summary: Model hub for Pytorch.
Home-page: https://gitee.com/summry/keras-model-hub
Author: summy
Author-email: fkfkfk2024@2925.com
License: UNKNOWN
Keywords: keras,AI,Machine learning,Deep learning,tensorflow,model,hub
Platform: UNKNOWN
Requires-Python: >=3.6
License-File: LICENSE
